array_api_jit/__init__.py
array_api_jit/_main.py
array_api_jit/py.typed
array_api_jit-1.0.0.dist-info/licenses/LICENSE
array_api_jit-1.0.0.dist-info/METADATA
array_api_jit-1.0.0.dist-info/WHEEL
array_api_jit-1.0.0.dist-info/top_level.txt
array_api_jit-1.0.0.dist-info/RECORD
