Metadata-Version: 2.4
Name: array-api-jit
Version: 1.0.0
Summary: JIT decorator supporting multiple array API compatible libraries
Author-email: 34j <34j.95a2p@simplelogin.com>
License: MIT
Project-URL: Bug Tracker, https://github.com/34j/array-api-jit/issues
Project-URL: Changelog, https://github.com/34j/array-api-jit/blob/main/CHANGELOG.md
Project-URL: documentation, https://array-api-jit.readthedocs.io
Project-URL: repository, https://github.com/34j/array-api-jit
Classifier: Development Status :: 2 - Pre-Alpha
Classifier: Intended Audience :: Developers
Classifier: Natural Language :: English
Classifier: Operating System :: OS Independent
Classifier: Programming Language :: Python :: 3.10
Classifier: Programming Language :: Python :: 3.11
Classifier: Programming Language :: Python :: 3.12
Classifier: Programming Language :: Python :: 3.13
Classifier: Topic :: Software Development :: Libraries
Requires-Python: >=3.10
License-File: LICENSE
Requires-Dist: array-api-compat>=1.11.2
Dynamic: license-file
